[
  {
    "exchange": "hyperliquid",
    "market_type": "CROSS",
    "symbol_raw": "BTC-USD",
    "leverage_max": 40,
    "price_usd": 114673.0,
    "volume_24h_usd": 2890388914.239176,
    "open_interest_base": 34015.9912999999,
    "open_interest_usd": 3900715770.3448887,
    "daily_snapshot": "2025-09-15"
  },
  {
    "exchange": "hyperliquid",
    "market_type": "CROSS",
    "symbol_raw": "ETH-USD",
    "leverage_max": 25,
    "price_usd": 4492.1,
    "volume_24h_usd": 2882478975.3366923,
    "open_interest_base": 814866.8872000002,
    "open_interest_usd": 3660463543.9911213,
    "daily_snapshot": "2025-09-15"
  },
  {
    "exchange": "hyperliquid",
    "market_type": "CROSS",
    "symbol_raw": "ATOM-USD",
    "leverage_max": 5,
    "price_usd": 4.5055,
    "volume_24h_usd": 788017.079392,
    "open_interest_base": 1323355.24,
    "open_interest_usd": 5962377.03382,
    "daily_snapshot": "2025-09-15"
  },
  {
    "exchange": "hyperliquid",
    "market_type": "CROSS",
    "symbol_raw": "MATIC-USD",
    "leverage_max": 20,
    "price_usd": 0.3754,
    "volume_24h_usd": 0.0,
    "open_interest_base": 0.0,
    "open_interest_usd": 0.0,
    "daily_snapshot": "2025-09-15"
  },
  {
    "exchange": "hyperliquid",
    "market_type": "CROSS",
    "symbol_raw": "DYDX-USD",
    "leverage_max": 5,
    "price_usd": 0.6076,
    "volume_24h_usd": 471497.0726450001,
    "open_interest_base": 2369203.3999999994,
    "open_interest_usd": 1439527.9858399997,
    "daily_snapshot": "2025-09-15"
  },
  {
    "exchange": "hyperliquid",
    "market_type": "CROSS",
    "symbol_raw": "SOL-USD",
    "leverage_max": 20,
    "price_usd": 233.82,
    "volume_24h_usd": 1491377264.4816046,
    "open_interest_base": 6781999.959999992,
    "open_interest_usd": 1585767230.647198,
    "daily_snapshot": "2025-09-15"
  },
  {
    "exchange": "hyperliquid",
    "market_type": "CROSS",
    "symbol_raw": "AVAX-USD",
    "leverage_max": 10,
    "price_usd": 28.57,
    "volume_24h_usd": 58161542.16752001,
    "open_interest_base": 3542205.8599999994,
    "open_interest_usd": 101200821.42019999,
    "daily_snapshot": "2025-09-15"
  },
  {
    "exchange": "hyperliquid",
    "market_type": "CROSS",
    "symbol_raw": "BNB-USD",
    "leverage_max": 10,
    "price_usd": 915.29,
    "volume_24h_usd": 22811643.62192,
    "open_interest_base": 70480.104,
    "open_interest_usd": 64509734.39016,
    "daily_snapshot": "2025-09-15"
  },
  {
    "exchange": "hyperliquid",
    "market_type": "CROSS",
    "symbol_raw": "APE-USD",
    "leverage_max": 5,
    "price_usd": 0.5756,
    "volume_24h_usd": 317049.5340349998,
    "open_interest_base": 2279498.6,
    "open_interest_usd": 1312079.3941600001,
    "daily_snapshot": "2025-09-15"
  },
  {
    "exchange": "hyperliquid",
    "market_type": "CROSS",
    "symbol_raw": "OP-USD",
    "leverage_max": 10,
    "price_usd": 0.7409,
    "volume_24h_usd": 3523297.6554020005,
    "open_interest_base": 8161081.800000003,
    "open_interest_usd": 6046545.505620002,
    "daily_snapshot": "2025-09-15"
  },
  {
    "exchange": "hyperliquid",
    "market_type": "CROSS",
    "symbol_raw": "LTC-USD",
    "leverage_max": 10,
    "price_usd": 112.88,
    "volume_24h_usd": 13039187.548099998,
    "open_interest_base": 565969.0000000001,
    "open_interest_usd": 63886580.72000001,
    "daily_snapshot": "2025-09-15"
  },
  {
    "exchange": "hyperliquid",
    "market_type": "CROSS",
    "symbol_raw": "ARB-USD",
    "leverage_max": 10,
    "price_usd": 0.49175,
    "volume_24h_usd": 12693677.886109,
    "open_interest_base": 50690120.199999996,
    "open_interest_usd": 24926866.608349998,
    "daily_snapshot": "2025-09-15"
  },
  {
    "exchange": "hyperliquid",
    "market_type": "CROSS",
    "symbol_raw": "DOGE-USD",
    "leverage_max": 10,
    "price_usd": 0.26301,
    "volume_24h_usd": 251179605.6180498,
    "open_interest_base": 1050923100.0,
    "open_interest_usd": 276403284.531,
    "daily_snapshot": "2025-09-15"
  },
  {
    "exchange": "hyperliquid",
    "market_type": "CROSS",
    "symbol_raw": "INJ-USD",
    "leverage_max": 10,
    "price_usd": 13.465,
    "volume_24h_usd": 3310358.4975999985,
    "open_interest_base": 571935.4,
    "open_interest_usd": 7701110.161,
    "daily_snapshot": "2025-09-15"
  },
  {
    "exchange": "hyperliquid",
    "market_type": "CROSS",
    "symbol_raw": "SUI-USD",
    "leverage_max": 10,
    "price_usd": 3.5095,
    "volume_24h_usd": 48932135.17428997,
    "open_interest_base": 30495519.2,
    "open_interest_usd": 107024024.6324,
    "daily_snapshot": "2025-09-15"
  },
  {
    "exchange": "hyperliquid",
    "market_type": "CROSS",
    "symbol_raw": "KPEPE-USD",
    "leverage_max": 10,
    "price_usd": 0.010683,
    "volume_24h_usd": 76056415.14194894,
    "open_interest_base": 12121633598.0,
    "open_interest_usd": 129495411.727434,
    "daily_snapshot": "2025-09-15"
  },
  {
    "exchange": "hyperliquid",
    "market_type": "CROSS",
    "symbol_raw": "CRV-USD",
    "leverage_max": 10,
    "price_usd": 0.7518,
    "volume_24h_usd": 12823829.020402003,
    "open_interest_base": 51577669.40000001,
    "open_interest_usd": 38776091.854920015,
    "daily_snapshot": "2025-09-15"
  },
  {
    "exchange": "hyperliquid",
    "market_type": "CROSS",
    "symbol_raw": "LDO-USD",
    "leverage_max": 10,
    "price_usd": 1.1761,
    "volume_24h_usd": 5457548.750990002,
    "open_interest_base": 26324924.4,
    "open_interest_usd": 30960743.586839996,
    "daily_snapshot": "2025-09-15"
  },
  {
    "exchange": "hyperliquid",
    "market_type": "CROSS",
    "symbol_raw": "LINK-USD",
    "leverage_max": 10,
    "price_usd": 23.18,
    "volume_24h_usd": 27492393.255499993,
    "open_interest_base": 4784814.2,
    "open_interest_usd": 110911993.156,
    "daily_snapshot": "2025-09-15"
  },
  {
    "exchange": "hyperliquid",
    "market_type": "CROSS",
    "symbol_raw": "STX-USD",
    "leverage_max": 5,
    "price_usd": 0.64005,
    "volume_24h_usd": 837546.5387119999,
    "open_interest_base": 2816094.6,
    "open_interest_usd": 1802441.34873,
    "daily_snapshot": "2025-09-15"
  },
  {
    "exchange": "hyperliquid",
    "market_type": "CROSS",
    "symbol_raw": "RNDR-USD",
    "leverage_max": 20,
    "price_usd": 7.03,
    "volume_24h_usd": 0.0,
    "open_interest_base": 0.0,
    "open_interest_usd": 0.0,
    "daily_snapshot": "2025-09-15"
  },
  {
    "exchange": "hyperliquid",
    "market_type": "CROSS",
    "symbol_raw": "CFX-USD",
    "leverage_max": 5,
    "price_usd": 0.17488,
    "volume_24h_usd": 670289.8818600003,
    "open_interest_base": 8180678.0,
    "open_interest_usd": 1430636.96864,
    "daily_snapshot": "2025-09-15"
  },
  {
    "exchange": "hyperliquid",
    "market_type": "CROSS",
    "symbol_raw": "FTM-USD",
    "leverage_max": 10,
    "price_usd": 0.712,
    "volume_24h_usd": 0.0,
    "open_interest_base": 0.0,
    "open_interest_usd": 0.0,
    "daily_snapshot": "2025-09-15"
  },
  {
    "exchange": "hyperliquid",
    "market_type": "CROSS",
    "symbol_raw": "GMX-USD",
    "leverage_max": 5,
    "price_usd": 14.965,
    "volume_24h_usd": 293658.4524600001,
    "open_interest_base": 89366.1,
    "open_interest_usd": 1337363.6865,
    "daily_snapshot": "2025-09-15"
  },
  {
    "exchange": "hyperliquid",
    "market_type": "CROSS",
    "symbol_raw": "SNX-USD",
    "leverage_max": 3,
    "price_usd": 0.66795,
    "volume_24h_usd": 83424.617834,
    "open_interest_base": 316591.6,
    "open_interest_usd": 211467.35921999998,
    "daily_snapshot": "2025-09-15"
  },
  {
    "exchange": "hyperliquid",
    "market_type": "CROSS",
    "symbol_raw": "XRP-USD",
    "leverage_max": 20,
    "price_usd": 3.0255,
    "volume_24h_usd": 197509380.11510032,
    "open_interest_base": 85720004.0,
    "open_interest_usd": 259345872.102,
    "daily_snapshot": "2025-09-15"
  },
  {
    "exchange": "hyperliquid",
    "market_type": "CROSS",
    "symbol_raw": "BCH-USD",
    "leverage_max": 10,
    "price_usd": 591.5,
    "volume_24h_usd": 6222247.50296,
    "open_interest_base": 16786.38,
    "open_interest_usd": 9929143.770000001,
    "daily_snapshot": "2025-09-15"
  },
  {
    "exchange": "hyperliquid",
    "market_type": "CROSS",
    "symbol_raw": "APT-USD",
    "leverage_max": 10,
    "price_usd": 4.353,
    "volume_24h_usd": 4204999.003061002,
    "open_interest_base": 3555275.8800000004,
    "open_interest_usd": 15476115.90564,
    "daily_snapshot": "2025-09-15"
  },
  {
    "exchange": "hyperliquid",
    "market_type": "CROSS",
    "symbol_raw": "AAVE-USD",
    "leverage_max": 10,
    "price_usd": 297.45,
    "volume_24h_usd": 18086739.501099996,
    "open_interest_base": 191653.24,
    "open_interest_usd": 57007256.238,
    "daily_snapshot": "2025-09-15"
  },
  {
    "exchange": "hyperliquid",
    "market_type": "CROSS",
    "symbol_raw": "COMP-USD",
    "leverage_max": 5,
    "price_usd": 43.605,
    "volume_24h_usd": 122513.44191,
    "open_interest_base": 23608.32,
    "open_interest_usd": 1029440.7935999999,
    "daily_snapshot": "2025-09-15"
  },
  {
    "exchange": "hyperliquid",
    "market_type": "CROSS",
    "symbol_raw": "MKR-USD",
    "leverage_max": 10,
    "price_usd": 1828.8,
    "volume_24h_usd": 0.0,
    "open_interest_base": 0.0,
    "open_interest_usd": 0.0,
    "daily_snapshot": "2025-09-15"
  },
  {
    "exchange": "hyperliquid",
    "market_type": "CROSS",
    "symbol_raw": "WLD-USD",
    "leverage_max": 10,
    "price_usd": 1.5044,
    "volume_24h_usd": 33263621.260549992,
    "open_interest_base": 44157119.40000001,
    "open_interest_usd": 66429970.42536002,
    "daily_snapshot": "2025-09-15"
  },
  {
    "exchange": "hyperliquid",
    "market_type": "CROSS",
    "symbol_raw": "FXS-USD",
    "leverage_max": 5,
    "price_usd": 2.68,
    "volume_24h_usd": 1798739.2894099997,
    "open_interest_base": 989372.6,
    "open_interest_usd": 2651518.568,
    "daily_snapshot": "2025-09-15"
  },
  {
    "exchange": "hyperliquid",
    "market_type": "CROSS",
    "symbol_raw": "HPOS-USD",
    "leverage_max": 3,
    "price_usd": 0.042203,
    "volume_24h_usd": 0.0,
    "open_interest_base": 0.0,
    "open_interest_usd": 0.0,
    "daily_snapshot": "2025-09-15"
  },
  {
    "exchange": "hyperliquid",
    "market_type": "CROSS",
    "symbol_raw": "RLB-USD",
    "leverage_max": 3,
    "price_usd": 0.071068,
    "volume_24h_usd": 0.0,
    "open_interest_base": 0.0,
    "open_interest_usd": 0.0,
    "daily_snapshot": "2025-09-15"
  },
  {
    "exchange": "hyperliquid",
    "market_type": "CROSS",
    "symbol_raw": "UNIBOT-USD",
    "leverage_max": 3,
    "price_usd": 6.053,
    "volume_24h_usd": 0.0,
    "open_interest_base": 0.0,
    "open_interest_usd": 0.0,
    "daily_snapshot": "2025-09-15"
  },
  {
    "exchange": "hyperliquid",
    "market_type": "CROSS",
    "symbol_raw": "YGG-USD",
    "leverage_max": 3,
    "price_usd": 0.20185,
    "volume_24h_usd": 1581413.3789900003,
    "open_interest_base": 3190186.0,
    "open_interest_usd": 643939.0441,
    "daily_snapshot": "2025-09-15"
  },
  {
    "exchange": "hyperliquid",
    "market_type": "CROSS",
    "symbol_raw": "TRX-USD",
    "leverage_max": 10,
    "price_usd": 0.34379,
    "volume_24h_usd": 2079681.8431700007,
    "open_interest_base": 51959702.0,
    "open_interest_usd": 17863225.95058,
    "daily_snapshot": "2025-09-15"
  },
  {
    "exchange": "hyperliquid",
    "market_type": "CROSS",
    "symbol_raw": "KSHIB-USD",
    "leverage_max": 10,
    "price_usd": 0.013036,
    "volume_24h_usd": 3293879.571566002,
    "open_interest_base": 515613430.0,
    "open_interest_usd": 6721536.67348,
    "daily_snapshot": "2025-09-15"
  },
  {
    "exchange": "hyperliquid",
    "market_type": "CROSS",
    "symbol_raw": "UNI-USD",
    "leverage_max": 10,
    "price_usd": 9.1145,
    "volume_24h_usd": 10921589.360099988,
    "open_interest_base": 2982047.2000000007,
    "open_interest_usd": 27179869.204400003,
    "daily_snapshot": "2025-09-15"
  },
  {
    "exchange": "hyperliquid",
    "market_type": "CROSS",
    "symbol_raw": "SEI-USD",
    "leverage_max": 10,
    "price_usd": 0.3161,
    "volume_24h_usd": 7256119.120379999,
    "open_interest_base": 52685624.0,
    "open_interest_usd": 16653925.746399999,
    "daily_snapshot": "2025-09-15"
  },
  {
    "exchange": "hyperliquid",
    "market_type": "CROSS",
    "symbol_raw": "RUNE-USD",
    "leverage_max": 5,
    "price_usd": 1.2544,
    "volume_24h_usd": 223944.22132,
    "open_interest_base": 1283522.5999999999,
    "open_interest_usd": 1610050.7494399997,
    "daily_snapshot": "2025-09-15"
  },
  {
    "exchange": "hyperliquid",
    "market_type": "CROSS",
    "symbol_raw": "OX-USD",
    "leverage_max": 3,
    "price_usd": 0.004982,
    "volume_24h_usd": 0.0,
    "open_interest_base": 0.0,
    "open_interest_usd": 0.0,
    "daily_snapshot": "2025-09-15"
  },
  {
    "exchange": "hyperliquid",
    "market_type": "CROSS",
    "symbol_raw": "FRIEND-USD",
    "leverage_max": 3,
    "price_usd": 0.47734,
    "volume_24h_usd": 0.0,
    "open_interest_base": 0.0,
    "open_interest_usd": 0.0,
    "daily_snapshot": "2025-09-15"
  },
  {
    "exchange": "hyperliquid",
    "market_type": "CROSS",
    "symbol_raw": "SHIA-USD",
    "leverage_max": 3,
    "price_usd": 0.000209,
    "volume_24h_usd": 0.0,
    "open_interest_base": 0.0,
    "open_interest_usd": 0.0,
    "daily_snapshot": "2025-09-15"
  },
  {
    "exchange": "hyperliquid",
    "market_type": "CROSS",
    "symbol_raw": "CYBER-USD",
    "leverage_max": 3,
    "price_usd": 1.043,
    "volume_24h_usd": 0.0,
    "open_interest_base": 0.0,
    "open_interest_usd": 0.0,
    "daily_snapshot": "2025-09-15"
  },
  {
    "exchange": "hyperliquid",
    "market_type": "CROSS",
    "symbol_raw": "ZRO-USD",
    "leverage_max": 5,
    "price_usd": 1.8865,
    "volume_24h_usd": 2237662.4329499993,
    "open_interest_base": 3683704.6,
    "open_interest_usd": 6949308.7279,
    "daily_snapshot": "2025-09-15"
  },
  {
    "exchange": "hyperliquid",
    "market_type": "CROSS",
    "symbol_raw": "BLZ-USD",
    "leverage_max": 5,
    "price_usd": 0.070028,
    "volume_24h_usd": 0.0,
    "open_interest_base": 0.0,
    "open_interest_usd": 0.0,
    "daily_snapshot": "2025-09-15"
  },
  {
    "exchange": "hyperliquid",
    "market_type": "CROSS",
    "symbol_raw": "DOT-USD",
    "leverage_max": 10,
    "price_usd": 4.1555,
    "volume_24h_usd": 5523716.04918,
    "open_interest_base": 1768875.0,
    "open_interest_usd": 7350560.0625,
    "daily_snapshot": "2025-09-15"
  },
  {
    "exchange": "hyperliquid",
    "market_type": "CROSS",
    "symbol_raw": "BANANA-USD",
    "leverage_max": 3,
    "price_usd": 21.535,
    "volume_24h_usd": 2075660.8372000002,
    "open_interest_base": 58877.6,
    "open_interest_usd": 1267929.116,
    "daily_snapshot": "2025-09-15"
  },
  {
    "exchange": "hyperliquid",
    "market_type": "CROSS",
    "symbol_raw": "TRB-USD",
    "leverage_max": 3,
    "price_usd": 34.655,
    "volume_24h_usd": 490958.0961200001,
    "open_interest_base": 19165.64,
    "open_interest_usd": 664185.2542,
    "daily_snapshot": "2025-09-15"
  },
  {
    "exchange": "hyperliquid",
    "market_type": "CROSS",
    "symbol_raw": "FTT-USD",
    "leverage_max": 3,
    "price_usd": 0.7833,
    "volume_24h_usd": 30300.74965,
    "open_interest_base": 287109.0,
    "open_interest_usd": 224892.4797,
    "daily_snapshot": "2025-09-15"
  },
  {
    "exchange": "hyperliquid",
    "market_type": "CROSS",
    "symbol_raw": "LOOM-USD",
    "leverage_max": 10,
    "price_usd": 0.071385,
    "volume_24h_usd": 0.0,
    "open_interest_base": 0.0,
    "open_interest_usd": 0.0,
    "daily_snapshot": "2025-09-15"
  },
  {
    "exchange": "hyperliquid",
    "market_type": "CROSS",
    "symbol_raw": "OGN-USD",
    "leverage_max": 3,
    "price_usd": 0.0558,
    "volume_24h_usd": 0.0,
    "open_interest_base": 0.0,
    "open_interest_usd": 0.0,
    "daily_snapshot": "2025-09-15"
  },
  {
    "exchange": "hyperliquid",
    "market_type": "CROSS",
    "symbol_raw": "RDNT-USD",
    "leverage_max": 5,
    "price_usd": 0.018338,
    "volume_24h_usd": 0.0,
    "open_interest_base": 0.0,
    "open_interest_usd": 0.0,
    "daily_snapshot": "2025-09-15"
  },
  {
    "exchange": "hyperliquid",
    "market_type": "CROSS",
    "symbol_raw": "ARK-USD",
    "leverage_max": 3,
    "price_usd": 0.4546,
    "volume_24h_usd": 453850.616,
    "open_interest_base": 1099756.0,
    "open_interest_usd": 499949.0776,
    "daily_snapshot": "2025-09-15"
  },
  {
    "exchange": "hyperliquid",
    "market_type": "CROSS",
    "symbol_raw": "BNT-USD",
    "leverage_max": 3,
    "price_usd": 0.38349,
    "volume_24h_usd": 0.0,
    "open_interest_base": 0.0,
    "open_interest_usd": 0.0,
    "daily_snapshot": "2025-09-15"
  },
  {
    "exchange": "hyperliquid",
    "market_type": "CROSS",
    "symbol_raw": "CANTO-USD",
    "leverage_max": 5,
    "price_usd": 0.06598,
    "volume_24h_usd": 0.0,
    "open_interest_base": 0.0,
    "open_interest_usd": 0.0,
    "daily_snapshot": "2025-09-15"
  },
  {
    "exchange": "hyperliquid",
    "market_type": "CROSS",
    "symbol_raw": "REQ-USD",
    "leverage_max": 3,
    "price_usd": 0.15423,
    "volume_24h_usd": 0.0,
    "open_interest_base": 0.0,
    "open_interest_usd": 0.0,
    "daily_snapshot": "2025-09-15"
  },
  {
    "exchange": "hyperliquid",
    "market_type": "CROSS",
    "symbol_raw": "BIGTIME-USD",
    "leverage_max": 5,
    "price_usd": 0.052139,
    "volume_24h_usd": 188240.477308,
    "open_interest_base": 54972096.0,
    "open_interest_usd": 2866190.1133439997,
    "daily_snapshot": "2025-09-15"
  },
  {
    "exchange": "hyperliquid",
    "market_type": "CROSS",
    "symbol_raw": "KAS-USD",
    "leverage_max": 3,
    "price_usd": 0.082659,
    "volume_24h_usd": 486409.1467689998,
    "open_interest_base": 18461778.0,
    "open_interest_usd": 1526032.1077019998,
    "daily_snapshot": "2025-09-15"
  },
  {
    "exchange": "hyperliquid",
    "market_type": "CROSS",
    "symbol_raw": "ORBS-USD",
    "leverage_max": 3,
    "price_usd": 0.019393,
    "volume_24h_usd": 0.0,
    "open_interest_base": 0.0,
    "open_interest_usd": 0.0,
    "daily_snapshot": "2025-09-15"
  },
  {
    "exchange": "hyperliquid",
    "market_type": "CROSS",
    "symbol_raw": "BLUR-USD",
    "leverage_max": 5,
    "price_usd": 0.081635,
    "volume_24h_usd": 630928.209525,
    "open_interest_base": 30159156.0,
    "open_interest_usd": 2462042.70006,
    "daily_snapshot": "2025-09-15"
  },
  {
    "exchange": "hyperliquid",
    "market_type": "CROSS",
    "symbol_raw": "TIA-USD",
    "leverage_max": 10,
    "price_usd": 1.686,
    "volume_24h_usd": 3785504.1567600016,
    "open_interest_base": 7597638.0,
    "open_interest_usd": 12809617.668,
    "daily_snapshot": "2025-09-15"
  },
  {
    "exchange": "hyperliquid",
    "market_type": "CROSS",
    "symbol_raw": "BSV-USD",
    "leverage_max": 3,
    "price_usd": 25.76,
    "volume_24h_usd": 96460.87633,
    "open_interest_base": 22623.18,
    "open_interest_usd": 582773.1168000001,
    "daily_snapshot": "2025-09-15"
  },
  {
    "exchange": "hyperliquid",
    "market_type": "CROSS",
    "symbol_raw": "ADA-USD",
    "leverage_max": 10,
    "price_usd": 0.8596,
    "volume_24h_usd": 17451075.20182001,
    "open_interest_base": 38245902.0,
    "open_interest_usd": 32876177.3592,
    "daily_snapshot": "2025-09-15"
  },
  {
    "exchange": "hyperliquid",
    "market_type": "CROSS",
    "symbol_raw": "TON-USD",
    "leverage_max": 10,
    "price_usd": 3.1415,
    "volume_24h_usd": 3297978.159089999,
    "open_interest_base": 9467436.4,
    "open_interest_usd": 29741951.450600002,
    "daily_snapshot": "2025-09-15"
  },
  {
    "exchange": "hyperliquid",
    "market_type": "CROSS",
    "symbol_raw": "MINA-USD",
    "leverage_max": 3,
    "price_usd": 0.1827,
    "volume_24h_usd": 70181.9451,
    "open_interest_base": 3035470.0,
    "open_interest_usd": 554580.369,
    "daily_snapshot": "2025-09-15"
  },
  {
    "exchange": "hyperliquid",
    "market_type": "CROSS",
    "symbol_raw": "POLYX-USD",
    "leverage_max": 3,
    "price_usd": 0.132,
    "volume_24h_usd": 44242.42535,
    "open_interest_base": 3515612.0,
    "open_interest_usd": 464060.78400000004,
    "daily_snapshot": "2025-09-15"
  },
  {
    "exchange": "hyperliquid",
    "market_type": "CROSS",
    "symbol_raw": "GAS-USD",
    "leverage_max": 3,
    "price_usd": 3.233,
    "volume_24h_usd": 55709.0934,
    "open_interest_base": 116411.2,
    "open_interest_usd": 376357.4096,
    "daily_snapshot": "2025-09-15"
  },
  {
    "exchange": "hyperliquid",
    "market_type": "CROSS",
    "symbol_raw": "PENDLE-USD",
    "leverage_max": 5,
    "price_usd": 4.842,
    "volume_24h_usd": 6120518.652699997,
    "open_interest_base": 4436096.0,
    "open_interest_usd": 21479576.832,
    "daily_snapshot": "2025-09-15"
  },
  {
    "exchange": "hyperliquid",
    "market_type": "CROSS",
    "symbol_raw": "STG-USD",
    "leverage_max": 3,
    "price_usd": 0.15385,
    "volume_24h_usd": 0.0,
    "open_interest_base": 0.0,
    "open_interest_usd": 0.0,
    "daily_snapshot": "2025-09-15"
  },
  {
    "exchange": "hyperliquid",
    "market_type": "CROSS",
    "symbol_raw": "FET-USD",
    "leverage_max": 5,
    "price_usd": 0.6355,
    "volume_24h_usd": 1012144.3195699991,
    "open_interest_base": 4713084.0,
    "open_interest_usd": 2995164.8819999998,
    "daily_snapshot": "2025-09-15"
  },
  {
    "exchange": "hyperliquid",
    "market_type": "CROSS",
    "symbol_raw": "STRAX-USD",
    "leverage_max": 10,
    "price_usd": 0.0416,
    "volume_24h_usd": 0.0,
    "open_interest_base": 0.0,
    "open_interest_usd": 0.0,
    "daily_snapshot": "2025-09-15"
  },
  {
    "exchange": "hyperliquid",
    "market_type": "CROSS",
    "symbol_raw": "NEAR-USD",
    "leverage_max": 10,
    "price_usd": 2.6115,
    "volume_24h_usd": 8159245.749450008,
    "open_interest_base": 5625389.0,
    "open_interest_usd": 14690703.373499999,
    "daily_snapshot": "2025-09-15"
  },
  {
    "exchange": "hyperliquid",
    "market_type": "CROSS",
    "symbol_raw": "MEME-USD",
    "leverage_max": 5,
    "price_usd": 0.002505,
    "volume_24h_usd": 430721.8104650001,
    "open_interest_base": 434753906.0,
    "open_interest_usd": 1089058.5345299998,
    "daily_snapshot": "2025-09-15"
  },
  {
    "exchange": "hyperliquid",
    "market_type": "CROSS",
    "symbol_raw": "ORDI-USD",
    "leverage_max": 5,
    "price_usd": 9.3905,
    "volume_24h_usd": 482229.148024,
    "open_interest_base": 112369.0,
    "open_interest_usd": 1055201.0945,
    "daily_snapshot": "2025-09-15"
  },
  {
    "exchange": "hyperliquid",
    "market_type": "CROSS",
    "symbol_raw": "BADGER-USD",
    "leverage_max": 5,
    "price_usd": 0.88959,
    "volume_24h_usd": 0.0,
    "open_interest_base": 0.0,
    "open_interest_usd": 0.0,
    "daily_snapshot": "2025-09-15"
  },
  {
    "exchange": "hyperliquid",
    "market_type": "CROSS",
    "symbol_raw": "NEO-USD",
    "leverage_max": 5,
    "price_usd": 6.499,
    "volume_24h_usd": 291650.806993,
    "open_interest_base": 81128.54,
    "open_interest_usd": 527254.38146,
    "daily_snapshot": "2025-09-15"
  },
  {
    "exchange": "hyperliquid",
    "market_type": "CROSS",
    "symbol_raw": "ZEN-USD",
    "leverage_max": 5,
    "price_usd": 7.2335,
    "volume_24h_usd": 160746.112333,
    "open_interest_base": 41428.14,
    "open_interest_usd": 299670.45069,
    "daily_snapshot": "2025-09-15"
  },
  {
    "exchange": "hyperliquid",
    "market_type": "CROSS",
    "symbol_raw": "FIL-USD",
    "leverage_max": 5,
    "price_usd": 2.4045,
    "volume_24h_usd": 711382.2896499998,
    "open_interest_base": 974677.6,
    "open_interest_usd": 2343612.2892,
    "daily_snapshot": "2025-09-15"
  },
  {
    "exchange": "hyperliquid",
    "market_type": "CROSS",
    "symbol_raw": "PYTH-USD",
    "leverage_max": 5,
    "price_usd": 0.15885,
    "volume_24h_usd": 2480937.5712400004,
    "open_interest_base": 28539034.0,
    "open_interest_usd": 4533425.5509,
    "daily_snapshot": "2025-09-15"
  },
  {
    "exchange": "hyperliquid",
    "market_type": "CROSS",
    "symbol_raw": "SUSHI-USD",
    "leverage_max": 5,
    "price_usd": 0.76564,
    "volume_24h_usd": 700684.7703990001,
    "open_interest_base": 871841.7999999999,
    "open_interest_usd": 667516.955752,
    "daily_snapshot": "2025-09-15"
  },
  {
    "exchange": "hyperliquid",
    "market_type": "CROSS",
    "symbol_raw": "ILV-USD",
    "leverage_max": 3,
    "price_usd": 12.14,
    "volume_24h_usd": 0.0,
    "open_interest_base": 0.0,
    "open_interest_usd": 0.0,
    "daily_snapshot": "2025-09-15"
  },
  {
    "exchange": "hyperliquid",
    "market_type": "CROSS",
    "symbol_raw": "IMX-USD",
    "leverage_max": 5,
    "price_usd": 0.62085,
    "volume_24h_usd": 1354096.4442050003,
    "open_interest_base": 2415858.8000000003,
    "open_interest_usd": 1499885.9359800003,
    "daily_snapshot": "2025-09-15"
  },
  {
    "exchange": "hyperliquid",
    "market_type": "CROSS",
    "symbol_raw": "KBONK-USD",
    "leverage_max": 10,
    "price_usd": 0.022892,
    "volume_24h_usd": 39734284.85473197,
    "open_interest_base": 2601722496.0,
    "open_interest_usd": 59558631.378432,
    "daily_snapshot": "2025-09-15"
  },
  {
    "exchange": "hyperliquid",
    "market_type": "CROSS",
    "symbol_raw": "GMT-USD",
    "leverage_max": 5,
    "price_usd": 0.04181,
    "volume_24h_usd": 121783.196544,
    "open_interest_base": 4767094.0,
    "open_interest_usd": 199312.20014,
    "daily_snapshot": "2025-09-15"
  },
  {
    "exchange": "hyperliquid",
    "market_type": "CROSS",
    "symbol_raw": "SUPER-USD",
    "leverage_max": 3,
    "price_usd": 0.59023,
    "volume_24h_usd": 362421.7008100001,
    "open_interest_base": 3001992.0,
    "open_interest_usd": 1771865.7381600002,
    "daily_snapshot": "2025-09-15"
  },
  {
    "exchange": "hyperliquid",
    "market_type": "CROSS",
    "symbol_raw": "USTC-USD",
    "leverage_max": 3,
    "price_usd": 0.012861,
    "volume_24h_usd": 183009.745756,
    "open_interest_base": 87293970.0,
    "open_interest_usd": 1122687.74817,
    "daily_snapshot": "2025-09-15"
  },
  {
    "exchange": "hyperliquid",
    "market_type": "CROSS",
    "symbol_raw": "NFTI-USD",
    "leverage_max": 3,
    "price_usd": 2518.4,
    "volume_24h_usd": 0.0,
    "open_interest_base": 0.0,
    "open_interest_usd": 0.0,
    "daily_snapshot": "2025-09-15"
  },
  {
    "exchange": "hyperliquid",
    "market_type": "CROSS",
    "symbol_raw": "JUP-USD",
    "leverage_max": 10,
    "price_usd": 0.5026,
    "volume_24h_usd": 5871865.9517800035,
    "open_interest_base": 29520010.0,
    "open_interest_usd": 14836757.026,
    "daily_snapshot": "2025-09-15"
  },
  {
    "exchange": "hyperliquid",
    "market_type": "CROSS",
    "symbol_raw": "KLUNC-USD",
    "leverage_max": 3,
    "price_usd": 0.05813,
    "volume_24h_usd": 110626.644901,
    "open_interest_base": 5264370.0,
    "open_interest_usd": 306017.8281,
    "daily_snapshot": "2025-09-15"
  },
  {
    "exchange": "hyperliquid",
    "market_type": "CROSS",
    "symbol_raw": "RSR-USD",
    "leverage_max": 3,
    "price_usd": 0.007405,
    "volume_24h_usd": 107635.699731,
    "open_interest_base": 107549336.0,
    "open_interest_usd": 796402.83308,
    "daily_snapshot": "2025-09-15"
  },
  {
    "exchange": "hyperliquid",
    "market_type": "CROSS",
    "symbol_raw": "GALA-USD",
    "leverage_max": 3,
    "price_usd": 0.01659,
    "volume_24h_usd": 545390.9166660002,
    "open_interest_base": 39830996.0,
    "open_interest_usd": 660796.22364,
    "daily_snapshot": "2025-09-15"
  },
  {
    "exchange": "hyperliquid",
    "market_type": "CROSS",
    "symbol_raw": "JTO-USD",
    "leverage_max": 5,
    "price_usd": 1.8315,
    "volume_24h_usd": 7552835.208099999,
    "open_interest_base": 3908090.0,
    "open_interest_usd": 7157666.835,
    "daily_snapshot": "2025-09-15"
  },
  {
    "exchange": "hyperliquid",
    "market_type": "CROSS",
    "symbol_raw": "NTRN-USD",
    "leverage_max": 3,
    "price_usd": 0.12385,
    "volume_24h_usd": 0.0,
    "open_interest_base": 0.0,
    "open_interest_usd": 0.0,
    "daily_snapshot": "2025-09-15"
  },
  {
    "exchange": "hyperliquid",
    "market_type": "CROSS",
    "symbol_raw": "ACE-USD",
    "leverage_max": 3,
    "price_usd": 0.6075,
    "volume_24h_usd": 805495.7094299998,
    "open_interest_base": 456956.58,
    "open_interest_usd": 277601.12235,
    "daily_snapshot": "2025-09-15"
  },
  {
    "exchange": "hyperliquid",
    "market_type": "CROSS",
    "symbol_raw": "MAV-USD",
    "leverage_max": 3,
    "price_usd": 0.067305,
    "volume_24h_usd": 546518.9781260001,
    "open_interest_base": 4117160.0,
    "open_interest_usd": 277105.4538,
    "daily_snapshot": "2025-09-15"
  },
  {
    "exchange": "hyperliquid",
    "market_type": "CROSS",
    "symbol_raw": "WIF-USD",
    "leverage_max": 10,
    "price_usd": 0.87782,
    "volume_24h_usd": 7013862.224330001,
    "open_interest_base": 25049196.0,
    "open_interest_usd": 21988685.232720003,
    "daily_snapshot": "2025-09-15"
  },
  {
    "exchange": "hyperliquid",
    "market_type": "CROSS",
    "symbol_raw": "CAKE-USD",
    "leverage_max": 3,
    "price_usd": 2.4455,
    "volume_24h_usd": 580851.34514,
    "open_interest_base": 622521.2,
    "open_interest_usd": 1522375.5946,
    "daily_snapshot": "2025-09-15"
  },
  {
    "exchange": "hyperliquid",
    "market_type": "CROSS",
    "symbol_raw": "PEOPLE-USD",
    "leverage_max": 3,
    "price_usd": 0.02011,
    "volume_24h_usd": 148793.3423960001,
    "open_interest_base": 33697852.0,
    "open_interest_usd": 677663.80372,
    "daily_snapshot": "2025-09-15"
  },
  {
    "exchange": "hyperliquid",
    "market_type": "CROSS",
    "symbol_raw": "ENS-USD",
    "leverage_max": 5,
    "price_usd": 22.97,
    "volume_24h_usd": 501552.9701799998,
    "open_interest_base": 517654.6,
    "open_interest_usd": 11890526.161999999,
    "daily_snapshot": "2025-09-15"
  },
  {
    "exchange": "hyperliquid",
    "market_type": "CROSS",
    "symbol_raw": "ETC-USD",
    "leverage_max": 5,
    "price_usd": 20.32,
    "volume_24h_usd": 675751.7768499999,
    "open_interest_base": 112177.8,
    "open_interest_usd": 2279452.896,
    "daily_snapshot": "2025-09-15"
  },
  {
    "exchange": "hyperliquid",
    "market_type": "CROSS",
    "symbol_raw": "XAI-USD",
    "leverage_max": 3,
    "price_usd": 0.04995,
    "volume_24h_usd": 556291.4651150001,
    "open_interest_base": 20278199.400000002,
    "open_interest_usd": 1012896.0600300002,
    "daily_snapshot": "2025-09-15"
  },
  {
    "exchange": "hyperliquid",
    "market_type": "CROSS",
    "symbol_raw": "MANTA-USD",
    "leverage_max": 3,
    "price_usd": 0.20575,
    "volume_24h_usd": 166813.0933600001,
    "open_interest_base": 1213542.6,
    "open_interest_usd": 249686.38995,
    "daily_snapshot": "2025-09-15"
  },
  {
    "exchange": "hyperliquid",
    "market_type": "CROSS",
    "symbol_raw": "UMA-USD",
    "leverage_max": 3,
    "price_usd": 1.325,
    "volume_24h_usd": 103547.08731,
    "open_interest_base": 406265.8,
    "open_interest_usd": 538302.1849999999,
    "daily_snapshot": "2025-09-15"
  },
  {
    "exchange": "hyperliquid",
    "market_type": "CROSS",
    "symbol_raw": "ONDO-USD",
    "leverage_max": 10,
    "price_usd": 1.0205,
    "volume_24h_usd": 10458600.829300001,
    "open_interest_base": 25180602.0,
    "open_interest_usd": 25696804.341,
    "daily_snapshot": "2025-09-15"
  },
  {
    "exchange": "hyperliquid",
    "market_type": "CROSS",
    "symbol_raw": "ALT-USD",
    "leverage_max": 5,
    "price_usd": 0.03273,
    "volume_24h_usd": 156144.122545,
    "open_interest_base": 31893790.0,
    "open_interest_usd": 1043883.7467,
    "daily_snapshot": "2025-09-15"
  },
  {
    "exchange": "hyperliquid",
    "market_type": "CROSS",
    "symbol_raw": "ZETA-USD",
    "leverage_max": 3,
    "price_usd": 0.185,
    "volume_24h_usd": 69752.309005,
    "open_interest_base": 4149830.4,
    "open_interest_usd": 767718.624,
    "daily_snapshot": "2025-09-15"
  },
  {
    "exchange": "hyperliquid",
    "market_type": "CROSS",
    "symbol_raw": "DYM-USD",
    "leverage_max": 3,
    "price_usd": 0.21445,
    "volume_24h_usd": 143664.9578899999,
    "open_interest_base": 3157554.0,
    "open_interest_usd": 677137.4553,
    "daily_snapshot": "2025-09-15"
  },
  {
    "exchange": "hyperliquid",
    "market_type": "CROSS",
    "symbol_raw": "MAVIA-USD",
    "leverage_max": 3,
    "price_usd": 0.1552,
    "volume_24h_usd": 389194.752254,
    "open_interest_base": 9336843.0,
    "open_interest_usd": 1449078.0336,
    "daily_snapshot": "2025-09-15"
  },
  {
    "exchange": "hyperliquid",
    "market_type": "CROSS",
    "symbol_raw": "W-USD",
    "leverage_max": 5,
    "price_usd": 0.08688,
    "volume_24h_usd": 457212.0687969998,
    "open_interest_base": 45858789.6,
    "open_interest_usd": 3984211.6404480003,
    "daily_snapshot": "2025-09-15"
  },
  {
    "exchange": "hyperliquid",
    "market_type": "CROSS",
    "symbol_raw": "PANDORA-USD",
    "leverage_max": 3,
    "price_usd": 1706.6,
    "volume_24h_usd": 0.0,
    "open_interest_base": 0.0,
    "open_interest_usd": 0.0,
    "daily_snapshot": "2025-09-15"
  },
  {
    "exchange": "hyperliquid",
    "market_type": "CROSS",
    "symbol_raw": "STRK-USD",
    "leverage_max": 5,
    "price_usd": 0.1329,
    "volume_24h_usd": 1280171.4728339997,
    "open_interest_base": 39489344.599999994,
    "open_interest_usd": 5248133.897339999,
    "daily_snapshot": "2025-09-15"
  },
  {
    "exchange": "hyperliquid",
    "market_type": "CROSS",
    "symbol_raw": "PIXEL-USD",
    "leverage_max": 3,
    "price_usd": 0.024025,
    "volume_24h_usd": 0.0,
    "open_interest_base": 0.0,
    "open_interest_usd": 0.0,
    "daily_snapshot": "2025-09-15"
  },
  {
    "exchange": "hyperliquid",
    "market_type": "CROSS",
    "symbol_raw": "AI-USD",
    "leverage_max": 3,
    "price_usd": 0.1257,
    "volume_24h_usd": 0.0,
    "open_interest_base": 0.0,
    "open_interest_usd": 0.0,
    "daily_snapshot": "2025-09-15"
  },
  {
    "exchange": "hyperliquid",
    "market_type": "CROSS",
    "symbol_raw": "TAO-USD",
    "leverage_max": 5,
    "price_usd": 338.9,
    "volume_24h_usd": 4211402.994030002,
    "open_interest_base": 81456.392,
    "open_interest_usd": 27605571.248800002,
    "daily_snapshot": "2025-09-15"
  },
  {
    "exchange": "hyperliquid",
    "market_type": "CROSS",
    "symbol_raw": "AR-USD",
    "leverage_max": 5,
    "price_usd": 6.918,
    "volume_24h_usd": 341763.9641830001,
    "open_interest_base": 348290.5600000001,
    "open_interest_usd": 2409474.0940800007,
    "daily_snapshot": "2025-09-15"
  },
  {
    "exchange": "hyperliquid",
    "market_type": "CROSS",
    "symbol_raw": "MYRO-USD",
    "leverage_max": 3,
    "price_usd": 0.015815,
    "volume_24h_usd": 0.0,
    "open_interest_base": 0.0,
    "open_interest_usd": 0.0,
    "daily_snapshot": "2025-09-15"
  },
  {
    "exchange": "hyperliquid",
    "market_type": "CROSS",
    "symbol_raw": "KFLOKI-USD",
    "leverage_max": 5,
    "price_usd": 0.094475,
    "volume_24h_usd": 1737370.003844,
    "open_interest_base": 30533014.0,
    "open_interest_usd": 2884606.4976500003,
    "daily_snapshot": "2025-09-15"
  },
  {
    "exchange": "hyperliquid",
    "market_type": "CROSS",
    "symbol_raw": "BOME-USD",
    "leverage_max": 3,
    "price_usd": 0.001971,
    "volume_24h_usd": 187565.289691,
    "open_interest_base": 236780182.0,
    "open_interest_usd": 466693.73872200004,
    "daily_snapshot": "2025-09-15"
  },
  {
    "exchange": "hyperliquid",
    "market_type": "CROSS",
    "symbol_raw": "ETHFI-USD",
    "leverage_max": 5,
    "price_usd": 1.4198,
    "volume_24h_usd": 3044277.131310001,
    "open_interest_base": 8072034.6,
    "open_interest_usd": 11460674.725079998,
    "daily_snapshot": "2025-09-15"
  },
  {
    "exchange": "hyperliquid",
    "market_type": "CROSS",
    "symbol_raw": "ENA-USD",
    "leverage_max": 10,
    "price_usd": 0.7137,
    "volume_24h_usd": 253670381.30732033,
    "open_interest_base": 567529216.0,
    "open_interest_usd": 405045601.4592,
    "daily_snapshot": "2025-09-15"
  },
  {
    "exchange": "hyperliquid",
    "market_type": "CROSS",
    "symbol_raw": "MNT-USD",
    "leverage_max": 5,
    "price_usd": 1.6641,
    "volume_24h_usd": 18234619.062879995,
    "open_interest_base": 21924029.200000003,
    "open_interest_usd": 36483776.991720006,
    "daily_snapshot": "2025-09-15"
  },
  {
    "exchange": "hyperliquid",
    "market_type": "CROSS",
    "symbol_raw": "TNSR-USD",
    "leverage_max": 3,
    "price_usd": 0.1168,
    "volume_24h_usd": 88729.198795,
    "open_interest_base": 4172918.2,
    "open_interest_usd": 487396.84576000005,
    "daily_snapshot": "2025-09-15"
  },
  {
    "exchange": "hyperliquid",
    "market_type": "CROSS",
    "symbol_raw": "SAGA-USD",
    "leverage_max": 5,
    "price_usd": 0.2458,
    "volume_24h_usd": 248092.572463,
    "open_interest_base": 2718178.6,
    "open_interest_usd": 668128.29988,
    "daily_snapshot": "2025-09-15"
  },
  {
    "exchange": "hyperliquid",
    "market_type": "CROSS",
    "symbol_raw": "MERL-USD",
    "leverage_max": 3,
    "price_usd": 0.15581,
    "volume_24h_usd": 402351.1373100001,
    "open_interest_base": 11905562.0,
    "open_interest_usd": 1855005.61522,
    "daily_snapshot": "2025-09-15"
  },
  {
    "exchange": "hyperliquid",
    "market_type": "CROSS",
    "symbol_raw": "HBAR-USD",
    "leverage_max": 5,
    "price_usd": 0.23252,
    "volume_24h_usd": 1125582.6071300001,
    "open_interest_base": 72722050.0,
    "open_interest_usd": 16909331.066,
    "daily_snapshot": "2025-09-15"
  },
  {
    "exchange": "hyperliquid",
    "market_type": "CROSS",
    "symbol_raw": "POPCAT-USD",
    "leverage_max": 10,
    "price_usd": 0.26225,
    "volume_24h_usd": 4825942.970529999,
    "open_interest_base": 62988212.0,
    "open_interest_usd": 16518658.597,
    "daily_snapshot": "2025-09-15"
  },
  {
    "exchange": "hyperliquid",
    "market_type": "CROSS",
    "symbol_raw": "OMNI-USD",
    "leverage_max": 3,
    "price_usd": 3.4423,
    "volume_24h_usd": 1032213.7981239997,
    "open_interest_base": 487253.9,
    "open_interest_usd": 1677274.09997,
    "daily_snapshot": "2025-09-15"
  },
  {
    "exchange": "hyperliquid",
    "market_type": "CROSS",
    "symbol_raw": "EIGEN-USD",
    "leverage_max": 5,
    "price_usd": 1.532,
    "volume_24h_usd": 9524519.115317006,
    "open_interest_base": 10866839.980000002,
    "open_interest_usd": 16647998.849360004,
    "daily_snapshot": "2025-09-15"
  },
  {
    "exchange": "hyperliquid",
    "market_type": "CROSS",
    "symbol_raw": "REZ-USD",
    "leverage_max": 3,
    "price_usd": 0.01128,
    "volume_24h_usd": 137378.380533,
    "open_interest_base": 36583628.0,
    "open_interest_usd": 412663.32384,
    "daily_snapshot": "2025-09-15"
  },
  {
    "exchange": "hyperliquid",
    "market_type": "CROSS",
    "symbol_raw": "NOT-USD",
    "leverage_max": 3,
    "price_usd": 0.001855,
    "volume_24h_usd": 229081.280032,
    "open_interest_base": 954182296.0,
    "open_interest_usd": 1770008.1590800001,
    "daily_snapshot": "2025-09-15"
  },
  {
    "exchange": "hyperliquid",
    "market_type": "CROSS",
    "symbol_raw": "TURBO-USD",
    "leverage_max": 5,
    "price_usd": 0.003988,
    "volume_24h_usd": 471334.2064729999,
    "open_interest_base": 386881368.0,
    "open_interest_usd": 1542882.895584,
    "daily_snapshot": "2025-09-15"
  },
  {
    "exchange": "hyperliquid",
    "market_type": "CROSS",
    "symbol_raw": "BRETT-USD",
    "leverage_max": 5,
    "price_usd": 0.05088,
    "volume_24h_usd": 1691503.8316029997,
    "open_interest_base": 71321038.0,
    "open_interest_usd": 3628814.4134400003,
    "daily_snapshot": "2025-09-15"
  },
  {
    "exchange": "hyperliquid",
    "market_type": "CROSS",
    "symbol_raw": "IO-USD",
    "leverage_max": 5,
    "price_usd": 0.6365,
    "volume_24h_usd": 2352451.516514999,
    "open_interest_base": 6521581.2,
    "open_interest_usd": 4150986.4337999998,
    "daily_snapshot": "2025-09-15"
  },
  {
    "exchange": "hyperliquid",
    "market_type": "CROSS",
    "symbol_raw": "ZK-USD",
    "leverage_max": 5,
    "price_usd": 0.05784,
    "volume_24h_usd": 451431.851503,
    "open_interest_base": 63996238.0,
    "open_interest_usd": 3701542.4059200003,
    "daily_snapshot": "2025-09-15"
  },
  {
    "exchange": "hyperliquid",
    "market_type": "CROSS",
    "symbol_raw": "BLAST-USD",
    "leverage_max": 3,
    "price_usd": 0.00242,
    "volume_24h_usd": 225449.536891,
    "open_interest_base": 764051738.0,
    "open_interest_usd": 1849005.20596,
    "daily_snapshot": "2025-09-15"
  },
  {
    "exchange": "hyperliquid",
    "market_type": "CROSS",
    "symbol_raw": "LISTA-USD",
    "leverage_max": 3,
    "price_usd": 0.1247,
    "volume_24h_usd": 0.0,
    "open_interest_base": 0.0,
    "open_interest_usd": 0.0,
    "daily_snapshot": "2025-09-15"
  },
  {
    "exchange": "hyperliquid",
    "market_type": "CROSS",
    "symbol_raw": "MEW-USD",
    "leverage_max": 5,
    "price_usd": 0.003003,
    "volume_24h_usd": 513884.750546,
    "open_interest_base": 140133710.0,
    "open_interest_usd": 420821.53113,
    "daily_snapshot": "2025-09-15"
  },
  {
    "exchange": "hyperliquid",
    "market_type": "CROSS",
    "symbol_raw": "RENDER-USD",
    "leverage_max": 5,
    "price_usd": 3.728,
    "volume_24h_usd": 974298.1858600002,
    "open_interest_base": 953456.9999999998,
    "open_interest_usd": 3554487.6959999995,
    "daily_snapshot": "2025-09-15"
  },
  {
    "exchange": "hyperliquid",
    "market_type": "CROSS",
    "symbol_raw": "KDOGS-USD",
    "leverage_max": 3,
    "price_usd": 0.13675,
    "volume_24h_usd": 0.0,
    "open_interest_base": 0.0,
    "open_interest_usd": 0.0,
    "daily_snapshot": "2025-09-15"
  },
  {
    "exchange": "hyperliquid",
    "market_type": "CROSS",
    "symbol_raw": "POL-USD",
    "leverage_max": 5,
    "price_usd": 0.2602,
    "volume_24h_usd": 1965099.1166,
    "open_interest_base": 19136454.0,
    "open_interest_usd": 4979305.3308,
    "daily_snapshot": "2025-09-15"
  },
  {
    "exchange": "hyperliquid",
    "market_type": "CROSS",
    "symbol_raw": "CATI-USD",
    "leverage_max": 3,
    "price_usd": 0.08275,
    "volume_24h_usd": 0.0,
    "open_interest_base": 0.0,
    "open_interest_usd": 0.0,
    "daily_snapshot": "2025-09-15"
  },
  {
    "exchange": "hyperliquid",
    "market_type": "CROSS",
    "symbol_raw": "CELO-USD",
    "leverage_max": 3,
    "price_usd": 0.3049,
    "volume_24h_usd": 64449.90044,
    "open_interest_base": 384280.0,
    "open_interest_usd": 117166.97200000001,
    "daily_snapshot": "2025-09-15"
  },
  {
    "exchange": "hyperliquid",
    "market_type": "CROSS",
    "symbol_raw": "HMSTR-USD",
    "leverage_max": 3,
    "price_usd": 0.000695,
    "volume_24h_usd": 100017.564305,
    "open_interest_base": 168844010.0,
    "open_interest_usd": 117346.58695,
    "daily_snapshot": "2025-09-15"
  },
  {
    "exchange": "hyperliquid",
    "market_type": "CROSS",
    "symbol_raw": "SCR-USD",
    "leverage_max": 5,
    "price_usd": 0.31758,
    "volume_24h_usd": 152645.492774,
    "open_interest_base": 1188321.2,
    "open_interest_usd": 377387.046696,
    "daily_snapshot": "2025-09-15"
  },
  {
    "exchange": "hyperliquid",
    "market_type": "CROSS",
    "symbol_raw": "NEIROETH-USD",
    "leverage_max": 5,
    "price_usd": 0.047395,
    "volume_24h_usd": 679257.1175139999,
    "open_interest_base": 34129660.0,
    "open_interest_usd": 1617575.2357,
    "daily_snapshot": "2025-09-15"
  },
  {
    "exchange": "hyperliquid",
    "market_type": "CROSS",
    "symbol_raw": "KNEIRO-USD",
    "leverage_max": 5,
    "price_usd": 0.34839,
    "volume_24h_usd": 384832.6222450002,
    "open_interest_base": 3419670.1999999997,
    "open_interest_usd": 1191378.900978,
    "daily_snapshot": "2025-09-15"
  },
  {
    "exchange": "hyperliquid",
    "market_type": "CROSS",
    "symbol_raw": "GOAT-USD",
    "leverage_max": 5,
    "price_usd": 0.097807,
    "volume_24h_usd": 1463276.8325460001,
    "open_interest_base": 27327326.0,
    "open_interest_usd": 2672803.7740820004,
    "daily_snapshot": "2025-09-15"
  },
  {
    "exchange": "hyperliquid",
    "market_type": "CROSS",
    "symbol_raw": "MOODENG-USD",
    "leverage_max": 5,
    "price_usd": 0.18558,
    "volume_24h_usd": 11223224.804449994,
    "open_interest_base": 33075632.0,
    "open_interest_usd": 6138175.78656,
    "daily_snapshot": "2025-09-15"
  },
  {
    "exchange": "hyperliquid",
    "market_type": "CROSS",
    "symbol_raw": "GRASS-USD",
    "leverage_max": 5,
    "price_usd": 0.76055,
    "volume_24h_usd": 1373127.8900230003,
    "open_interest_base": 6567033.0,
    "open_interest_usd": 4994556.94815,
    "daily_snapshot": "2025-09-15"
  },
  {
    "exchange": "hyperliquid",
    "market_type": "CROSS",
    "symbol_raw": "PURR-USD",
    "leverage_max": 3,
    "price_usd": 0.17828,
    "volume_24h_usd": 2367978.638949999,
    "open_interest_base": 100600364.0,
    "open_interest_usd": 17935032.89392,
    "daily_snapshot": "2025-09-15"
  },
  {
    "exchange": "hyperliquid",
    "market_type": "CROSS",
    "symbol_raw": "PNUT-USD",
    "leverage_max": 5,
    "price_usd": 0.2352,
    "volume_24h_usd": 1062000.840542,
    "open_interest_base": 10199099.400000002,
    "open_interest_usd": 2398828.1788800005,
    "daily_snapshot": "2025-09-15"
  },
  {
    "exchange": "hyperliquid",
    "market_type": "CROSS",
    "symbol_raw": "XLM-USD",
    "leverage_max": 5,
    "price_usd": 0.3783,
    "volume_24h_usd": 3075527.5271600005,
    "open_interest_base": 17058032.0,
    "open_interest_usd": 6453053.505600001,
    "daily_snapshot": "2025-09-15"
  },
  {
    "exchange": "hyperliquid",
    "market_type": "CROSS",
    "symbol_raw": "CHILLGUY-USD",
    "leverage_max": 3,
    "price_usd": 0.04585,
    "volume_24h_usd": 1232032.824294,
    "open_interest_base": 116384786.0,
    "open_interest_usd": 5336242.4381,
    "daily_snapshot": "2025-09-15"
  },
  {
    "exchange": "hyperliquid",
    "market_type": "CROSS",
    "symbol_raw": "SAND-USD",
    "leverage_max": 5,
    "price_usd": 0.29465,
    "volume_24h_usd": 308655.5151199999,
    "open_interest_base": 3348578.0,
    "open_interest_usd": 986658.5077000001,
    "daily_snapshot": "2025-09-15"
  },
  {
    "exchange": "hyperliquid",
    "market_type": "CROSS",
    "symbol_raw": "IOTA-USD",
    "leverage_max": 3,
    "price_usd": 0.1867,
    "volume_24h_usd": 165037.79267,
    "open_interest_base": 2591500.0,
    "open_interest_usd": 483833.05,
    "daily_snapshot": "2025-09-15"
  },
  {
    "exchange": "hyperliquid",
    "market_type": "CROSS",
    "symbol_raw": "ALGO-USD",
    "leverage_max": 5,
    "price_usd": 0.2312,
    "volume_24h_usd": 720656.2036600003,
    "open_interest_base": 10880686.0,
    "open_interest_usd": 2515614.6032,
    "daily_snapshot": "2025-09-15"
  },
  {
    "exchange": "hyperliquid",
    "market_type": "CROSS",
    "symbol_raw": "HYPE-USD",
    "leverage_max": 10,
    "price_usd": 52.98,
    "volume_24h_usd": 506831155.87867963,
    "open_interest_base": 26427085.580000006,
    "open_interest_usd": 1400106994.0284002,
    "daily_snapshot": "2025-09-15"
  },
  {
    "exchange": "hyperliquid",
    "market_type": "CROSS",
    "symbol_raw": "ME-USD",
    "leverage_max": 5,
    "price_usd": 0.67455,
    "volume_24h_usd": 1088097.659312,
    "open_interest_base": 6360822.6,
    "open_interest_usd": 4290692.88483,
    "daily_snapshot": "2025-09-15"
  },
  {
    "exchange": "hyperliquid",
    "market_type": "CROSS",
    "symbol_raw": "MOVE-USD",
    "leverage_max": 5,
    "price_usd": 0.12481,
    "volume_24h_usd": 277496.2819600001,
    "open_interest_base": 13200042.0,
    "open_interest_usd": 1647497.24202,
    "daily_snapshot": "2025-09-15"
  },
  {
    "exchange": "hyperliquid",
    "market_type": "CROSS",
    "symbol_raw": "VIRTUAL-USD",
    "leverage_max": 5,
    "price_usd": 1.2078,
    "volume_24h_usd": 4337407.32344,
    "open_interest_base": 11176955.6,
    "open_interest_usd": 13499526.973679999,
    "daily_snapshot": "2025-09-15"
  },
  {
    "exchange": "hyperliquid",
    "market_type": "CROSS",
    "symbol_raw": "PENGU-USD",
    "leverage_max": 5,
    "price_usd": 0.032722,
    "volume_24h_usd": 34364005.48212101,
    "open_interest_base": 1707502546.0,
    "open_interest_usd": 55872898.310212,
    "daily_snapshot": "2025-09-15"
  },
  {
    "exchange": "hyperliquid",
    "market_type": "CROSS",
    "symbol_raw": "USUAL-USD",
    "leverage_max": 5,
    "price_usd": 0.06235,
    "volume_24h_usd": 375339.7787729998,
    "open_interest_base": 18665614.200000003,
    "open_interest_usd": 1163801.0453700002,
    "daily_snapshot": "2025-09-15"
  },
  {
    "exchange": "hyperliquid",
    "market_type": "CROSS",
    "symbol_raw": "FARTCOIN-USD",
    "leverage_max": 10,
    "price_usd": 0.81217,
    "volume_24h_usd": 104169586.61088201,
    "open_interest_base": 339235373.3999999,
    "open_interest_usd": 275516793.2142779,
    "daily_snapshot": "2025-09-15"
  },
  {
    "exchange": "hyperliquid",
    "market_type": "CROSS",
    "symbol_raw": "AI16Z-USD",
    "leverage_max": 5,
    "price_usd": 0.10505,
    "volume_24h_usd": 4298550.498934001,
    "open_interest_base": 33638077.4,
    "open_interest_usd": 3533680.03087,
    "daily_snapshot": "2025-09-15"
  },
  {
    "exchange": "hyperliquid",
    "market_type": "CROSS",
    "symbol_raw": "AIXBT-USD",
    "leverage_max": 5,
    "price_usd": 0.11133,
    "volume_24h_usd": 1192232.4053999998,
    "open_interest_base": 15146884.0,
    "open_interest_usd": 1686302.5957199999,
    "daily_snapshot": "2025-09-15"
  },
  {
    "exchange": "hyperliquid",
    "market_type": "CROSS",
    "symbol_raw": "ZEREBRO-USD",
    "leverage_max": 5,
    "price_usd": 0.02022,
    "volume_24h_usd": 289621.927558,
    "open_interest_base": 58633396.0,
    "open_interest_usd": 1185567.26712,
    "daily_snapshot": "2025-09-15"
  },
  {
    "exchange": "hyperliquid",
    "market_type": "CROSS",
    "symbol_raw": "BIO-USD",
    "leverage_max": 5,
    "price_usd": 0.1583,
    "volume_24h_usd": 4370153.387300003,
    "open_interest_base": 30225488.0,
    "open_interest_usd": 4784694.7504,
    "daily_snapshot": "2025-09-15"
  },
  {
    "exchange": "hyperliquid",
    "market_type": "CROSS",
    "symbol_raw": "GRIFFAIN-USD",
    "leverage_max": 5,
    "price_usd": 0.039006,
    "volume_24h_usd": 1097010.0374949994,
    "open_interest_base": 94520118.0,
    "open_interest_usd": 3686851.722708,
    "daily_snapshot": "2025-09-15"
  },
  {
    "exchange": "hyperliquid",
    "market_type": "CROSS",
    "symbol_raw": "SPX-USD",
    "leverage_max": 5,
    "price_usd": 1.2776,
    "volume_24h_usd": 6487927.31037,
    "open_interest_base": 10852159.399999997,
    "open_interest_usd": 13864718.849439997,
    "daily_snapshot": "2025-09-15"
  },
  {
    "exchange": "hyperliquid",
    "market_type": "CROSS",
    "symbol_raw": "S-USD",
    "leverage_max": 5,
    "price_usd": 0.29775,
    "volume_24h_usd": 1308282.51671,
    "open_interest_base": 39127626.0,
    "open_interest_usd": 11650250.6415,
    "daily_snapshot": "2025-09-15"
  },
  {
    "exchange": "hyperliquid",
    "market_type": "CROSS",
    "symbol_raw": "MORPHO-USD",
    "leverage_max": 5,
    "price_usd": 1.9623,
    "volume_24h_usd": 1893636.0590700004,
    "open_interest_base": 3635837.0,
    "open_interest_usd": 7134602.9451,
    "daily_snapshot": "2025-09-15"
  },
  {
    "exchange": "hyperliquid",
    "market_type": "CROSS",
    "symbol_raw": "TRUMP-USD",
    "leverage_max": 10,
    "price_usd": 8.4835,
    "volume_24h_usd": 5571921.265009998,
    "open_interest_base": 3120527.2,
    "open_interest_usd": 26472992.501199998,
    "daily_snapshot": "2025-09-15"
  },
  {
    "exchange": "hyperliquid",
    "market_type": "CROSS",
    "symbol_raw": "MELANIA-USD",
    "leverage_max": 5,
    "price_usd": 0.19593,
    "volume_24h_usd": 2103685.266663001,
    "open_interest_base": 25717348.799999997,
    "open_interest_usd": 5038800.150384,
    "daily_snapshot": "2025-09-15"
  },
  {
    "exchange": "hyperliquid",
    "market_type": "CROSS",
    "symbol_raw": "ANIME-USD",
    "leverage_max": 3,
    "price_usd": 0.01517,
    "volume_24h_usd": 302440.778555,
    "open_interest_base": 107233788.0,
    "open_interest_usd": 1626736.56396,
    "daily_snapshot": "2025-09-15"
  },
  {
    "exchange": "hyperliquid",
    "market_type": "CROSS",
    "symbol_raw": "VINE-USD",
    "leverage_max": 5,
    "price_usd": 0.071895,
    "volume_24h_usd": 2723583.202170998,
    "open_interest_base": 74202806.0,
    "open_interest_usd": 5334810.73737,
    "daily_snapshot": "2025-09-15"
  },
  {
    "exchange": "hyperliquid",
    "market_type": "CROSS",
    "symbol_raw": "VVV-USD",
    "leverage_max": 3,
    "price_usd": 2.513,
    "volume_24h_usd": 160875.824617,
    "open_interest_base": 1267612.8200000003,
    "open_interest_usd": 3185511.0166600007,
    "daily_snapshot": "2025-09-15"
  },
  {
    "exchange": "hyperliquid",
    "market_type": "CROSS",
    "symbol_raw": "JELLY-USD",
    "leverage_max": 3,
    "price_usd": 0.03719,
    "volume_24h_usd": 0.0,
    "open_interest_base": 0.0,
    "open_interest_usd": 0.0,
    "daily_snapshot": "2025-09-15"
  },
  {
    "exchange": "hyperliquid",
    "market_type": "CROSS",
    "symbol_raw": "BERA-USD",
    "leverage_max": 5,
    "price_usd": 2.3105,
    "volume_24h_usd": 2686689.1432199986,
    "open_interest_base": 9192251.6,
    "open_interest_usd": 21238697.3218,
    "daily_snapshot": "2025-09-15"
  },
  {
    "exchange": "hyperliquid",
    "market_type": "CROSS",
    "symbol_raw": "TST-USD",
    "leverage_max": 3,
    "price_usd": 0.02674,
    "volume_24h_usd": 621091.6767300002,
    "open_interest_base": 19656798.0,
    "open_interest_usd": 525622.77852,
    "daily_snapshot": "2025-09-15"
  },
  {
    "exchange": "hyperliquid",
    "market_type": "CROSS",
    "symbol_raw": "LAYER-USD",
    "leverage_max": 3,
    "price_usd": 0.5228,
    "volume_24h_usd": 116215.22927,
    "open_interest_base": 1478798.0,
    "open_interest_usd": 773115.5944000001,
    "daily_snapshot": "2025-09-15"
  },
  {
    "exchange": "hyperliquid",
    "market_type": "CROSS",
    "symbol_raw": "IP-USD",
    "leverage_max": 3,
    "price_usd": 9.6731,
    "volume_24h_usd": 5523994.598090003,
    "open_interest_base": 4714754.6,
    "open_interest_usd": 45606292.72126,
    "daily_snapshot": "2025-09-15"
  },
  {
    "exchange": "hyperliquid",
    "market_type": "CROSS",
    "symbol_raw": "OM-USD",
    "leverage_max": 5,
    "price_usd": 0.20545,
    "volume_24h_usd": 1042441.485119,
    "open_interest_base": 15995632.600000001,
    "open_interest_usd": 3286302.71767,
    "daily_snapshot": "2025-09-15"
  },
  {
    "exchange": "hyperliquid",
    "market_type": "CROSS",
    "symbol_raw": "KAITO-USD",
    "leverage_max": 5,
    "price_usd": 1.1187,
    "volume_24h_usd": 1562073.5537000007,
    "open_interest_base": 4756612.0,
    "open_interest_usd": 5321221.8444,
    "daily_snapshot": "2025-09-15"
  },
  {
    "exchange": "hyperliquid",
    "market_type": "CROSS",
    "symbol_raw": "NIL-USD",
    "leverage_max": 3,
    "price_usd": 0.3147,
    "volume_24h_usd": 279956.1135900001,
    "open_interest_base": 8173576.0,
    "open_interest_usd": 2572224.3671999997,
    "daily_snapshot": "2025-09-15"
  },
  {
    "exchange": "hyperliquid",
    "market_type": "CROSS",
    "symbol_raw": "PAXG-USD",
    "leverage_max": 5,
    "price_usd": 3677.2,
    "volume_24h_usd": 5205015.644799999,
    "open_interest_base": 7931.248,
    "open_interest_usd": 29164785.1456,
    "daily_snapshot": "2025-09-15"
  },
  {
    "exchange": "hyperliquid",
    "market_type": "CROSS",
    "symbol_raw": "PROMPT-USD",
    "leverage_max": 5,
    "price_usd": 0.16723,
    "volume_24h_usd": 1204877.3597300001,
    "open_interest_base": 27326124.0,
    "open_interest_usd": 4569747.716519999,
    "daily_snapshot": "2025-09-15"
  },
  {
    "exchange": "hyperliquid",
    "market_type": "CROSS",
    "symbol_raw": "BABY-USD",
    "leverage_max": 5,
    "price_usd": 0.04861,
    "volume_24h_usd": 150190.090887,
    "open_interest_base": 19568016.0,
    "open_interest_usd": 951201.2577600001,
    "daily_snapshot": "2025-09-15"
  },
  {
    "exchange": "hyperliquid",
    "market_type": "CROSS",
    "symbol_raw": "WCT-USD",
    "leverage_max": 3,
    "price_usd": 0.29345,
    "volume_24h_usd": 295258.1955800001,
    "open_interest_base": 4101714.0,
    "open_interest_usd": 1203647.9733,
    "daily_snapshot": "2025-09-15"
  },
  {
    "exchange": "hyperliquid",
    "market_type": "CROSS",
    "symbol_raw": "HYPER-USD",
    "leverage_max": 3,
    "price_usd": 0.30216,
    "volume_24h_usd": 333744.0801799998,
    "open_interest_base": 6081094.0,
    "open_interest_usd": 1837463.36304,
    "daily_snapshot": "2025-09-15"
  },
  {
    "exchange": "hyperliquid",
    "market_type": "CROSS",
    "symbol_raw": "ZORA-USD",
    "leverage_max": 3,
    "price_usd": 0.075225,
    "volume_24h_usd": 24269584.221237987,
    "open_interest_base": 296904618.0,
    "open_interest_usd": 22334649.88905,
    "daily_snapshot": "2025-09-15"
  },
  {
    "exchange": "hyperliquid",
    "market_type": "CROSS",
    "symbol_raw": "INIT-USD",
    "leverage_max": 3,
    "price_usd": 0.349,
    "volume_24h_usd": 354792.82452,
    "open_interest_base": 11933472.0,
    "open_interest_usd": 4164781.7279999997,
    "daily_snapshot": "2025-09-15"
  },
  {
    "exchange": "hyperliquid",
    "market_type": "CROSS",
    "symbol_raw": "DOOD-USD",
    "leverage_max": 3,
    "price_usd": 0.003664,
    "volume_24h_usd": 283336.079731,
    "open_interest_base": 125338686.0,
    "open_interest_usd": 459240.945504,
    "daily_snapshot": "2025-09-15"
  },
  {
    "exchange": "hyperliquid",
    "market_type": "CROSS",
    "symbol_raw": "LAUNCHCOIN-USD",
    "leverage_max": 3,
    "price_usd": 0.0847,
    "volume_24h_usd": 9209524.293786999,
    "open_interest_base": 438063932.0,
    "open_interest_usd": 37104015.0404,
    "daily_snapshot": "2025-09-15"
  },
  {
    "exchange": "hyperliquid",
    "market_type": "CROSS",
    "symbol_raw": "NXPC-USD",
    "leverage_max": 5,
    "price_usd": 0.67725,
    "volume_24h_usd": 378968.7963700001,
    "open_interest_base": 2947746.0,
    "open_interest_usd": 1996360.9785,
    "daily_snapshot": "2025-09-15"
  },
  {
    "exchange": "hyperliquid",
    "market_type": "CROSS",
    "symbol_raw": "SOPH-USD",
    "leverage_max": 5,
    "price_usd": 0.03051,
    "volume_24h_usd": 337515.6662550002,
    "open_interest_base": 40947450.0,
    "open_interest_usd": 1249306.6994999999,
    "daily_snapshot": "2025-09-15"
  },
  {
    "exchange": "hyperliquid",
    "market_type": "CROSS",
    "symbol_raw": "RESOLV-USD",
    "leverage_max": 3,
    "price_usd": 0.1487,
    "volume_24h_usd": 624942.2315100001,
    "open_interest_base": 25499354.0,
    "open_interest_usd": 3791753.9398,
    "daily_snapshot": "2025-09-15"
  },
  {
    "exchange": "hyperliquid",
    "market_type": "CROSS",
    "symbol_raw": "SYRUP-USD",
    "leverage_max": 3,
    "price_usd": 0.44209,
    "volume_24h_usd": 1971415.3147500006,
    "open_interest_base": 9896648.0,
    "open_interest_usd": 4375209.11432,
    "daily_snapshot": "2025-09-15"
  },
  {
    "exchange": "hyperliquid",
    "market_type": "CROSS",
    "symbol_raw": "PUMP-USD",
    "leverage_max": 5,
    "price_usd": 0.008397,
    "volume_24h_usd": 593176220.8415967,
    "open_interest_base": 80347560824.0,
    "open_interest_usd": 674678468.239128,
    "daily_snapshot": "2025-09-15"
  },
  {
    "exchange": "hyperliquid",
    "market_type": "CROSS",
    "symbol_raw": "PROVE-USD",
    "leverage_max": 3,
    "price_usd": 0.8771,
    "volume_24h_usd": 1380220.5608200014,
    "open_interest_base": 1794626.0,
    "open_interest_usd": 1574066.4646,
    "daily_snapshot": "2025-09-15"
  },
  {
    "exchange": "hyperliquid",
    "market_type": "CROSS",
    "symbol_raw": "YZY-USD",
    "leverage_max": 3,
    "price_usd": 0.4473,
    "volume_24h_usd": 1632593.6206800004,
    "open_interest_base": 6494398.0,
    "open_interest_usd": 2904944.2254,
    "daily_snapshot": "2025-09-15"
  },
  {
    "exchange": "hyperliquid",
    "market_type": "CROSS",
    "symbol_raw": "XPL-USD",
    "leverage_max": 3,
    "price_usd": 0.76754,
    "volume_24h_usd": 10002836.0591,
    "open_interest_base": 155896286.0,
    "open_interest_usd": 119656635.35644,
    "daily_snapshot": "2025-09-15"
  },
  {
    "exchange": "hyperliquid",
    "market_type": "CROSS",
    "symbol_raw": "WLFI-USD",
    "leverage_max": 5,
    "price_usd": 0.22145,
    "volume_24h_usd": 63080133.0086601,
    "open_interest_base": 414020562.0,
    "open_interest_usd": 91684853.4549,
    "daily_snapshot": "2025-09-15"
  },
  {
    "exchange": "hyperliquid",
    "market_type": "CROSS",
    "symbol_raw": "LINEA-USD",
    "leverage_max": 3,
    "price_usd": 0.026578,
    "volume_24h_usd": 43673813.18379104,
    "open_interest_base": 813235926.0,
    "open_interest_usd": 21614184.441228002,
    "daily_snapshot": "2025-09-15"
  }
]